etcmaint/__init__.py
etcmaint/__main__.py
etcmaint/etcmaint.py
etcmaint/tests/__init__.py
etcmaint/tests/test_commands.py
etcmaint-0.8.dist-info/entry_points.txt
etcmaint-0.8.dist-info/LICENSE
etcmaint-0.8.dist-info/WHEEL
etcmaint-0.8.dist-info/METADATA
etcmaint-0.8.dist-info/RECORD
