Metadata-Version: 2.1
Name: etcmaint
Version: 0.8
Summary: An Arch Linux tool based on git for the maintenance of /etc files.
Home-page: https://gitlab.com/xdegaye/etcmaint
Keywords: ArchLinux pacman
Author: Xavier de Gaye
Author-email: xdegaye@gmail.com
Requires-Python: >=3.6
Classifier: License :: OSI Approved :: MIT License
Classifier: Programming Language :: Python :: 3
Classifier: Topic :: System :: Software Distribution
Requires-Dist: zstandard
Project-URL: Documentation, https://xdegaye.gitlab.io/etcmaint/
